{
 "cells": [
  {
   "cell_type": "code",
   "id": "initial_id",
   "metadata": {
    "collapsed": true,
    "ExecuteTime": {
     "end_time": "2025-05-03T13:58:32.763470Z",
     "start_time": "2025-05-03T13:58:32.759197Z"
    }
   },
   "source": [
    "source = \"\"\"\n",
    "PI = 3.14\n",
    "\n",
    "def circle_area(r):\n",
    "    return PI * r ** 2\n",
    "\n",
    "class Dog(object):\n",
    "\n",
    "    def __init__(self, name):\n",
    "        self.name = name\n",
    "\n",
    "    def yelp(self):\n",
    "        print('woof, i am', self.name)\n",
    "\"\"\"\n",
    "code = compile(source, filename=\"<string>\", mode=\"exec\")\n",
    "print(code)"
   ],
   "outputs": [
    {
     "name": "stdout",
     "output_type": "stream",
     "text": [
      "<code object <module> at 0x7ff12d040d50, file \"<string>\", line 1>\n"
     ]
    }
   ],
   "execution_count": 25
  },
  {
   "metadata": {
    "ExecuteTime": {
     "end_time": "2025-05-03T13:58:32.827870Z",
     "start_time": "2025-05-03T13:58:32.823262Z"
    }
   },
   "cell_type": "code",
   "source": [
    "print(code.co_code)\n",
    "print(code.co_consts)\n",
    "print(code.co_names)\n",
    "print(code.co_varnames)\n",
    "print(code.co_filename)\n",
    "print(code.co_firstlineno)\n",
    "print(code.co_lnotab)\n",
    "print(code.co_freevars)\n",
    "print(code.co_cellvars)\n"
   ],
   "id": "409e20e263955a55",
   "outputs": [
    {
     "name": "stdout",
     "output_type": "stream",
     "text": [
      "b'\\x97\\x00d\\x00Z\\x00d\\x01\\x84\\x00Z\\x01\\x02\\x00G\\x00d\\x02\\x84\\x00d\\x03e\\x02\\xa6\\x03\\x00\\x00\\xab\\x03\\x00\\x00\\x00\\x00\\x00\\x00\\x00\\x00Z\\x03d\\x04S\\x00'\n",
      "(3.14, <code object circle_area at 0x7ff12eb026b0, file \"<string>\", line 4>, <code object Dog at 0x7ff12e9509d0, file \"<string>\", line 7>, 'Dog', None)\n",
      "('PI', 'circle_area', 'object', 'Dog')\n",
      "()\n",
      "<string>\n",
      "1\n",
      "b'\\x00\\xff\\x02\\x02\\x04\\x02\\x06\\x03'\n",
      "()\n",
      "()\n"
     ]
    }
   ],
   "execution_count": 26
  },
  {
   "metadata": {
    "ExecuteTime": {
     "end_time": "2025-05-03T13:58:32.875585Z",
     "start_time": "2025-05-03T13:58:32.871884Z"
    }
   },
   "cell_type": "code",
   "source": [
    "dog_code = code.co_consts[2]\n",
    "print(dog_code)\n",
    "print(dog_code.co_consts)"
   ],
   "id": "ec14b56d100f1fc0",
   "outputs": [
    {
     "name": "stdout",
     "output_type": "stream",
     "text": [
      "<code object Dog at 0x7ff12e9509d0, file \"<string>\", line 7>\n",
      "('Dog', <code object __init__ at 0x7ff12e94c370, file \"<string>\", line 9>, <code object yelp at 0x7ff148d82b50, file \"<string>\", line 12>, None)\n"
     ]
    }
   ],
   "execution_count": 27
  },
  {
   "metadata": {
    "ExecuteTime": {
     "end_time": "2025-05-03T13:58:32.940294Z",
     "start_time": "2025-05-03T13:58:32.934313Z"
    }
   },
   "cell_type": "code",
   "source": [
    "import dis\n",
    "dis.dis(code)"
   ],
   "id": "a43023766650d479",
   "outputs": [
    {
     "name": "stdout",
     "output_type": "stream",
     "text": [
      "  0           0 RESUME                   0\n",
      "\n",
      "  2           2 LOAD_CONST               0 (3.14)\n",
      "              4 STORE_NAME               0 (PI)\n",
      "\n",
      "  4           6 LOAD_CONST               1 (<code object circle_area at 0x7ff12eb026b0, file \"<string>\", line 4>)\n",
      "              8 MAKE_FUNCTION            0\n",
      "             10 STORE_NAME               1 (circle_area)\n",
      "\n",
      "  7          12 PUSH_NULL\n",
      "             14 LOAD_BUILD_CLASS\n",
      "             16 LOAD_CONST               2 (<code object Dog at 0x7ff12e9509d0, file \"<string>\", line 7>)\n",
      "             18 MAKE_FUNCTION            0\n",
      "             20 LOAD_CONST               3 ('Dog')\n",
      "             22 LOAD_NAME                2 (object)\n",
      "             24 PRECALL                  3\n",
      "             28 CALL                     3\n",
      "             38 STORE_NAME               3 (Dog)\n",
      "             40 LOAD_CONST               4 (None)\n",
      "             42 RETURN_VALUE\n",
      "\n",
      "Disassembly of <code object circle_area at 0x7ff12eb026b0, file \"<string>\", line 4>:\n",
      "  4           0 RESUME                   0\n",
      "\n",
      "  5           2 LOAD_GLOBAL              0 (PI)\n",
      "             14 LOAD_FAST                0 (r)\n",
      "             16 LOAD_CONST               1 (2)\n",
      "             18 BINARY_OP                8 (**)\n",
      "             22 BINARY_OP                5 (*)\n",
      "             26 RETURN_VALUE\n",
      "\n",
      "Disassembly of <code object Dog at 0x7ff12e9509d0, file \"<string>\", line 7>:\n",
      "  7           0 RESUME                   0\n",
      "              2 LOAD_NAME                0 (__name__)\n",
      "              4 STORE_NAME               1 (__module__)\n",
      "              6 LOAD_CONST               0 ('Dog')\n",
      "              8 STORE_NAME               2 (__qualname__)\n",
      "\n",
      "  9          10 LOAD_CONST               1 (<code object __init__ at 0x7ff12e94c370, file \"<string>\", line 9>)\n",
      "             12 MAKE_FUNCTION            0\n",
      "             14 STORE_NAME               3 (__init__)\n",
      "\n",
      " 12          16 LOAD_CONST               2 (<code object yelp at 0x7ff148d82b50, file \"<string>\", line 12>)\n",
      "             18 MAKE_FUNCTION            0\n",
      "             20 STORE_NAME               4 (yelp)\n",
      "             22 LOAD_CONST               3 (None)\n",
      "             24 RETURN_VALUE\n",
      "\n",
      "Disassembly of <code object __init__ at 0x7ff12e94c370, file \"<string>\", line 9>:\n",
      "  9           0 RESUME                   0\n",
      "\n",
      " 10           2 LOAD_FAST                1 (name)\n",
      "              4 LOAD_FAST                0 (self)\n",
      "              6 STORE_ATTR               0 (name)\n",
      "             16 LOAD_CONST               0 (None)\n",
      "             18 RETURN_VALUE\n",
      "\n",
      "Disassembly of <code object yelp at 0x7ff148d82b50, file \"<string>\", line 12>:\n",
      " 12           0 RESUME                   0\n",
      "\n",
      " 13           2 LOAD_GLOBAL              1 (NULL + print)\n",
      "             14 LOAD_CONST               1 ('woof, i am')\n",
      "             16 LOAD_FAST                0 (self)\n",
      "             18 LOAD_ATTR                1 (name)\n",
      "             28 PRECALL                  2\n",
      "             32 CALL                     2\n",
      "             42 POP_TOP\n",
      "             44 LOAD_CONST               0 (None)\n",
      "             46 RETURN_VALUE\n"
     ]
    }
   ],
   "execution_count": 28
  },
  {
   "metadata": {
    "ExecuteTime": {
     "end_time": "2025-05-03T13:58:32.988164Z",
     "start_time": "2025-05-03T13:58:32.983161Z"
    }
   },
   "cell_type": "code",
   "source": [
    "code =\"\"\"\n",
    "import sys as s\n",
    "\"\"\"\n",
    "code = compile(code, filename=\"<string>\", mode=\"exec\")\n",
    "print(code.co_consts)\n",
    "print(code.co_names)\n",
    "dis.dis(code)"
   ],
   "id": "8317da2a02b68a9b",
   "outputs": [
    {
     "name": "stdout",
     "output_type": "stream",
     "text": [
      "(0, None)\n",
      "('sys', 's')\n",
      "  0           0 RESUME                   0\n",
      "\n",
      "  2           2 LOAD_CONST               0 (0)\n",
      "              4 LOAD_CONST               1 (None)\n",
      "              6 IMPORT_NAME              0 (sys)\n",
      "              8 STORE_NAME               1 (s)\n",
      "             10 LOAD_CONST               1 (None)\n",
      "             12 RETURN_VALUE\n"
     ]
    }
   ],
   "execution_count": 29
  },
  {
   "metadata": {
    "ExecuteTime": {
     "end_time": "2025-05-03T13:58:33.053087Z",
     "start_time": "2025-05-03T13:58:33.047584Z"
    }
   },
   "cell_type": "code",
   "source": [
    "code = \"\"\"\n",
    "pi = 3.14\n",
    "def circle_area(r):\n",
    "    return pi * r ** 2\n",
    "\n",
    "circle_area(2)\n",
    "\"\"\"\n",
    "code = compile(code, filename=\"<string>\", mode=\"exec\")\n",
    "print(code.co_consts)\n",
    "print(code.co_names)\n",
    "dis.dis(code)"
   ],
   "id": "948ebbb9d73f2eb",
   "outputs": [
    {
     "name": "stdout",
     "output_type": "stream",
     "text": [
      "(3.14, <code object circle_area at 0x7ff12e950ab0, file \"<string>\", line 3>, 2, None)\n",
      "('pi', 'circle_area')\n",
      "  0           0 RESUME                   0\n",
      "\n",
      "  2           2 LOAD_CONST               0 (3.14)\n",
      "              4 STORE_NAME               0 (pi)\n",
      "\n",
      "  3           6 LOAD_CONST               1 (<code object circle_area at 0x7ff12e950ab0, file \"<string>\", line 3>)\n",
      "              8 MAKE_FUNCTION            0\n",
      "             10 STORE_NAME               1 (circle_area)\n",
      "\n",
      "  6          12 PUSH_NULL\n",
      "             14 LOAD_NAME                1 (circle_area)\n",
      "             16 LOAD_CONST               2 (2)\n",
      "             18 PRECALL                  1\n",
      "             22 CALL                     1\n",
      "             32 POP_TOP\n",
      "             34 LOAD_CONST               3 (None)\n",
      "             36 RETURN_VALUE\n",
      "\n",
      "Disassembly of <code object circle_area at 0x7ff12e950ab0, file \"<string>\", line 3>:\n",
      "  3           0 RESUME                   0\n",
      "\n",
      "  4           2 LOAD_GLOBAL              0 (pi)\n",
      "             14 LOAD_FAST                0 (r)\n",
      "             16 LOAD_CONST               1 (2)\n",
      "             18 BINARY_OP                8 (**)\n",
      "             22 BINARY_OP                5 (*)\n",
      "             26 RETURN_VALUE\n"
     ]
    }
   ],
   "execution_count": 30
  },
  {
   "metadata": {
    "ExecuteTime": {
     "end_time": "2025-05-03T13:58:33.102175Z",
     "start_time": "2025-05-03T13:58:33.097170Z"
    }
   },
   "cell_type": "code",
   "source": [
    "code = \"\"\"\n",
    "def adder(n):\n",
    "    def handler(x):\n",
    "        return n+x\n",
    "    return handler\n",
    "\n",
    "add10 = adder(10)\n",
    "print(add10(100))\n",
    "print(add10.__closure__)\n",
    "print(add10.__closure__[0].cell_contents)\n",
    "add10.__closure__[0].cell_contents = 1000\n",
    "print(add10(1))\n",
    "\"\"\"\n",
    "code = compile(code, filename=\"<string>\", mode=\"exec\")\n",
    "print(code.co_consts)\n",
    "print(code.co_names)\n",
    "print(code.co_consts[1])\n",
    "exec(code, globals(),{})\n",
    "# dis.dis(code)"
   ],
   "id": "9d639b299bd3a8e2",
   "outputs": [
    {
     "name": "stdout",
     "output_type": "stream",
     "text": [
      "(<code object adder at 0x7ff148d069a0, file \"<string>\", line 2>, 10, 100, 0, 1000, 1, None)\n",
      "('adder', 'add10', 'print', '__closure__', 'cell_contents')\n",
      "10\n",
      "110\n",
      "(<cell at 0x7ff12edeecb0: int object at 0x7ff154cf6028>,)\n",
      "10\n",
      "1001\n"
     ]
    }
   ],
   "execution_count": 31
  },
  {
   "metadata": {
    "ExecuteTime": {
     "end_time": "2025-05-04T11:22:24.587654Z",
     "start_time": "2025-05-04T11:22:24.577988Z"
    }
   },
   "cell_type": "code",
   "source": [
    "code =\"\"\"class Dog:\n",
    "    def __init__(self, name):\n",
    "        self.name = name\n",
    "    def yelp(self):\n",
    "        print(f'woof by {self.name}')\n",
    "dog = Dog('dog')\n",
    "dog.yelp()\n",
    "def yelp2(self):\n",
    "    print(f'woof 2 by {self.name}')\n",
    "Dog.yelp2 = yelp2\n",
    "dog.yelp2()\"\"\"\n",
    "code = compile(code, filename=\"<string>\", mode=\"exec\")\n",
    "\n",
    "print(code.co_consts)\n",
    "print(code.co_names)\n",
    "print(code.co_consts[0])\n",
    "exec(code, globals(),{})\n",
    "print(dis.dis(code))"
   ],
   "id": "dd12f5ee7d6d9f7a",
   "outputs": [
    {
     "name": "stdout",
     "output_type": "stream",
     "text": [
      "(<code object Dog at 0x7ff12eb026b0, file \"<string>\", line 1>, 'Dog', 'dog', <code object yelp2 at 0x7ff12d040f30, file \"<string>\", line 8>, None)\n",
      "('Dog', 'dog', 'yelp', 'yelp2')\n",
      "<code object Dog at 0x7ff12eb026b0, file \"<string>\", line 1>\n",
      "woof by dog\n",
      "woof 2 by dog\n",
      "  0           0 RESUME                   0\n",
      "\n",
      "  1           2 PUSH_NULL\n",
      "              4 LOAD_BUILD_CLASS\n",
      "              6 LOAD_CONST               0 (<code object Dog at 0x7ff12eb026b0, file \"<string>\", line 1>)\n",
      "              8 MAKE_FUNCTION            0\n",
      "             10 LOAD_CONST               1 ('Dog')\n",
      "             12 PRECALL                  2\n",
      "             16 CALL                     2\n",
      "             26 STORE_NAME               0 (Dog)\n",
      "\n",
      "  6          28 PUSH_NULL\n",
      "             30 LOAD_NAME                0 (Dog)\n",
      "             32 LOAD_CONST               2 ('dog')\n",
      "             34 PRECALL                  1\n",
      "             38 CALL                     1\n",
      "             48 STORE_NAME               1 (dog)\n",
      "\n",
      "  7          50 LOAD_NAME                1 (dog)\n",
      "             52 LOAD_METHOD              2 (yelp)\n",
      "             74 PRECALL                  0\n",
      "             78 CALL                     0\n",
      "             88 POP_TOP\n",
      "\n",
      "  8          90 LOAD_CONST               3 (<code object yelp2 at 0x7ff12d040f30, file \"<string>\", line 8>)\n",
      "             92 MAKE_FUNCTION            0\n",
      "             94 STORE_NAME               3 (yelp2)\n",
      "\n",
      " 10          96 LOAD_NAME                3 (yelp2)\n",
      "             98 LOAD_NAME                0 (Dog)\n",
      "            100 STORE_ATTR               3 (yelp2)\n",
      "\n",
      " 11         110 LOAD_NAME                1 (dog)\n",
      "            112 LOAD_METHOD              3 (yelp2)\n",
      "            134 PRECALL                  0\n",
      "            138 CALL                     0\n",
      "            148 POP_TOP\n",
      "            150 LOAD_CONST               4 (None)\n",
      "            152 RETURN_VALUE\n",
      "\n",
      "Disassembly of <code object Dog at 0x7ff12eb026b0, file \"<string>\", line 1>:\n",
      "  1           0 RESUME                   0\n",
      "              2 LOAD_NAME                0 (__name__)\n",
      "              4 STORE_NAME               1 (__module__)\n",
      "              6 LOAD_CONST               0 ('Dog')\n",
      "              8 STORE_NAME               2 (__qualname__)\n",
      "\n",
      "  2          10 LOAD_CONST               1 (<code object __init__ at 0x7ff148d05fe0, file \"<string>\", line 2>)\n",
      "             12 MAKE_FUNCTION            0\n",
      "             14 STORE_NAME               3 (__init__)\n",
      "\n",
      "  4          16 LOAD_CONST               2 (<code object yelp at 0x7ff12d0414d0, file \"<string>\", line 4>)\n",
      "             18 MAKE_FUNCTION            0\n",
      "             20 STORE_NAME               4 (yelp)\n",
      "             22 LOAD_CONST               3 (None)\n",
      "             24 RETURN_VALUE\n",
      "\n",
      "Disassembly of <code object __init__ at 0x7ff148d05fe0, file \"<string>\", line 2>:\n",
      "  2           0 RESUME                   0\n",
      "\n",
      "  3           2 LOAD_FAST                1 (name)\n",
      "              4 LOAD_FAST                0 (self)\n",
      "              6 STORE_ATTR               0 (name)\n",
      "             16 LOAD_CONST               0 (None)\n",
      "             18 RETURN_VALUE\n",
      "\n",
      "Disassembly of <code object yelp at 0x7ff12d0414d0, file \"<string>\", line 4>:\n",
      "  4           0 RESUME                   0\n",
      "\n",
      "  5           2 LOAD_GLOBAL              1 (NULL + print)\n",
      "             14 LOAD_CONST               1 ('woof by ')\n",
      "             16 LOAD_FAST                0 (self)\n",
      "             18 LOAD_ATTR                1 (name)\n",
      "             28 FORMAT_VALUE             0\n",
      "             30 BUILD_STRING             2\n",
      "             32 PRECALL                  1\n",
      "             36 CALL                     1\n",
      "             46 POP_TOP\n",
      "             48 LOAD_CONST               0 (None)\n",
      "             50 RETURN_VALUE\n",
      "\n",
      "Disassembly of <code object yelp2 at 0x7ff12d040f30, file \"<string>\", line 8>:\n",
      "  8           0 RESUME                   0\n",
      "\n",
      "  9           2 LOAD_GLOBAL              1 (NULL + print)\n",
      "             14 LOAD_CONST               1 ('woof 2 by ')\n",
      "             16 LOAD_FAST                0 (self)\n",
      "             18 LOAD_ATTR                1 (name)\n",
      "             28 FORMAT_VALUE             0\n",
      "             30 BUILD_STRING             2\n",
      "             32 PRECALL                  1\n",
      "             36 CALL                     1\n",
      "             46 POP_TOP\n",
      "             48 LOAD_CONST               0 (None)\n",
      "             50 RETURN_VALUE\n",
      "None\n"
     ]
    }
   ],
   "execution_count": 34
  },
  {
   "metadata": {
    "ExecuteTime": {
     "end_time": "2025-05-04T12:02:24.113087Z",
     "start_time": "2025-05-04T12:02:24.098058Z"
    }
   },
   "cell_type": "code",
   "source": [
    "code = \"\"\"class Animal:\n",
    "    def run(self):\n",
    "        print('running')\n",
    "\n",
    "class Dog(Animal):\n",
    "    def yelp(self):\n",
    "        print('woof')\n",
    "    def play(self):\n",
    "        print('playing')\n",
    "\n",
    "class Sleuth(Dog):\n",
    "    def yelp(self):\n",
    "        print('WOOF!')\n",
    "    def hunt(self):\n",
    "        print('hunting')\n",
    "\n",
    "class SnifferDog(Dog):\n",
    "    def search(self):\n",
    "        print('searching')\n",
    "\n",
    "class PoliceDog(Sleuth, SnifferDog):\n",
    "    def patrol(self):\n",
    "        print('patroling')\n",
    "\n",
    "print(PoliceDog.__base__)\n",
    "print(PoliceDog.__bases__)\n",
    "print(PoliceDog.__mro__)\n",
    "\"\"\"\n",
    "code = compile(code, filename=\"<string>\", mode=\"exec\")\n",
    "exec (code, globals(),{})\n",
    "print(dis.dis(code))"
   ],
   "id": "19aef8c860a0fd3d",
   "outputs": [
    {
     "name": "stdout",
     "output_type": "stream",
     "text": [
      "<class '__main__.Sleuth'>\n",
      "(<class '__main__.Sleuth'>, <class '__main__.SnifferDog'>)\n",
      "(<class '__main__.PoliceDog'>, <class '__main__.Sleuth'>, <class '__main__.SnifferDog'>, <class '__main__.Dog'>, <class '__main__.Animal'>, <class 'object'>)\n",
      "  0           0 RESUME                   0\n",
      "\n",
      "  1           2 PUSH_NULL\n",
      "              4 LOAD_BUILD_CLASS\n",
      "              6 LOAD_CONST               0 (<code object Animal at 0x7ff12e94ec10, file \"<string>\", line 1>)\n",
      "              8 MAKE_FUNCTION            0\n",
      "             10 LOAD_CONST               1 ('Animal')\n",
      "             12 PRECALL                  2\n",
      "             16 CALL                     2\n",
      "             26 STORE_NAME               0 (Animal)\n",
      "\n",
      "  5          28 PUSH_NULL\n",
      "             30 LOAD_BUILD_CLASS\n",
      "             32 LOAD_CONST               2 (<code object Dog at 0x7ff12e9502d0, file \"<string>\", line 5>)\n",
      "             34 MAKE_FUNCTION            0\n",
      "             36 LOAD_CONST               3 ('Dog')\n",
      "             38 LOAD_NAME                0 (Animal)\n",
      "             40 PRECALL                  3\n",
      "             44 CALL                     3\n",
      "             54 STORE_NAME               1 (Dog)\n",
      "\n",
      " 11          56 PUSH_NULL\n",
      "             58 LOAD_BUILD_CLASS\n",
      "             60 LOAD_CONST               4 (<code object Sleuth at 0x7ff12e951450, file \"<string>\", line 11>)\n",
      "             62 MAKE_FUNCTION            0\n",
      "             64 LOAD_CONST               5 ('Sleuth')\n",
      "             66 LOAD_NAME                1 (Dog)\n",
      "             68 PRECALL                  3\n",
      "             72 CALL                     3\n",
      "             82 STORE_NAME               2 (Sleuth)\n",
      "\n",
      " 17          84 PUSH_NULL\n",
      "             86 LOAD_BUILD_CLASS\n",
      "             88 LOAD_CONST               6 (<code object SnifferDog at 0x7ff12e94c6b0, file \"<string>\", line 17>)\n",
      "             90 MAKE_FUNCTION            0\n",
      "             92 LOAD_CONST               7 ('SnifferDog')\n",
      "             94 LOAD_NAME                1 (Dog)\n",
      "             96 PRECALL                  3\n",
      "            100 CALL                     3\n",
      "            110 STORE_NAME               3 (SnifferDog)\n",
      "\n",
      " 21         112 PUSH_NULL\n",
      "            114 LOAD_BUILD_CLASS\n",
      "            116 LOAD_CONST               8 (<code object PoliceDog at 0x7ff12e94e800, file \"<string>\", line 21>)\n",
      "            118 MAKE_FUNCTION            0\n",
      "            120 LOAD_CONST               9 ('PoliceDog')\n",
      "            122 LOAD_NAME                2 (Sleuth)\n",
      "            124 LOAD_NAME                3 (SnifferDog)\n",
      "            126 PRECALL                  4\n",
      "            130 CALL                     4\n",
      "            140 STORE_NAME               4 (PoliceDog)\n",
      "\n",
      " 25         142 PUSH_NULL\n",
      "            144 LOAD_NAME                5 (print)\n",
      "            146 LOAD_NAME                4 (PoliceDog)\n",
      "            148 LOAD_ATTR                6 (__base__)\n",
      "            158 PRECALL                  1\n",
      "            162 CALL                     1\n",
      "            172 POP_TOP\n",
      "\n",
      " 26         174 PUSH_NULL\n",
      "            176 LOAD_NAME                5 (print)\n",
      "            178 LOAD_NAME                4 (PoliceDog)\n",
      "            180 LOAD_ATTR                7 (__bases__)\n",
      "            190 PRECALL                  1\n",
      "            194 CALL                     1\n",
      "            204 POP_TOP\n",
      "\n",
      " 27         206 PUSH_NULL\n",
      "            208 LOAD_NAME                5 (print)\n",
      "            210 LOAD_NAME                4 (PoliceDog)\n",
      "            212 LOAD_ATTR                8 (__mro__)\n",
      "            222 PRECALL                  1\n",
      "            226 CALL                     1\n",
      "            236 POP_TOP\n",
      "            238 LOAD_CONST              10 (None)\n",
      "            240 RETURN_VALUE\n",
      "\n",
      "Disassembly of <code object Animal at 0x7ff12e94ec10, file \"<string>\", line 1>:\n",
      "  1           0 RESUME                   0\n",
      "              2 LOAD_NAME                0 (__name__)\n",
      "              4 STORE_NAME               1 (__module__)\n",
      "              6 LOAD_CONST               0 ('Animal')\n",
      "              8 STORE_NAME               2 (__qualname__)\n",
      "\n",
      "  2          10 LOAD_CONST               1 (<code object run at 0x7ff12e9516f0, file \"<string>\", line 2>)\n",
      "             12 MAKE_FUNCTION            0\n",
      "             14 STORE_NAME               3 (run)\n",
      "             16 LOAD_CONST               2 (None)\n",
      "             18 RETURN_VALUE\n",
      "\n",
      "Disassembly of <code object run at 0x7ff12e9516f0, file \"<string>\", line 2>:\n",
      "  2           0 RESUME                   0\n",
      "\n",
      "  3           2 LOAD_GLOBAL              1 (NULL + print)\n",
      "             14 LOAD_CONST               1 ('running')\n",
      "             16 PRECALL                  1\n",
      "             20 CALL                     1\n",
      "             30 POP_TOP\n",
      "             32 LOAD_CONST               0 (None)\n",
      "             34 RETURN_VALUE\n",
      "\n",
      "Disassembly of <code object Dog at 0x7ff12e9502d0, file \"<string>\", line 5>:\n",
      "  5           0 RESUME                   0\n",
      "              2 LOAD_NAME                0 (__name__)\n",
      "              4 STORE_NAME               1 (__module__)\n",
      "              6 LOAD_CONST               0 ('Dog')\n",
      "              8 STORE_NAME               2 (__qualname__)\n",
      "\n",
      "  6          10 LOAD_CONST               1 (<code object yelp at 0x7ff12e951990, file \"<string>\", line 6>)\n",
      "             12 MAKE_FUNCTION            0\n",
      "             14 STORE_NAME               3 (yelp)\n",
      "\n",
      "  8          16 LOAD_CONST               2 (<code object play at 0x7ff12e951370, file \"<string>\", line 8>)\n",
      "             18 MAKE_FUNCTION            0\n",
      "             20 STORE_NAME               4 (play)\n",
      "             22 LOAD_CONST               3 (None)\n",
      "             24 RETURN_VALUE\n",
      "\n",
      "Disassembly of <code object yelp at 0x7ff12e951990, file \"<string>\", line 6>:\n",
      "  6           0 RESUME                   0\n",
      "\n",
      "  7           2 LOAD_GLOBAL              1 (NULL + print)\n",
      "             14 LOAD_CONST               1 ('woof')\n",
      "             16 PRECALL                  1\n",
      "             20 CALL                     1\n",
      "             30 POP_TOP\n",
      "             32 LOAD_CONST               0 (None)\n",
      "             34 RETURN_VALUE\n",
      "\n",
      "Disassembly of <code object play at 0x7ff12e951370, file \"<string>\", line 8>:\n",
      "  8           0 RESUME                   0\n",
      "\n",
      "  9           2 LOAD_GLOBAL              1 (NULL + print)\n",
      "             14 LOAD_CONST               1 ('playing')\n",
      "             16 PRECALL                  1\n",
      "             20 CALL                     1\n",
      "             30 POP_TOP\n",
      "             32 LOAD_CONST               0 (None)\n",
      "             34 RETURN_VALUE\n",
      "\n",
      "Disassembly of <code object Sleuth at 0x7ff12e951450, file \"<string>\", line 11>:\n",
      " 11           0 RESUME                   0\n",
      "              2 LOAD_NAME                0 (__name__)\n",
      "              4 STORE_NAME               1 (__module__)\n",
      "              6 LOAD_CONST               0 ('Sleuth')\n",
      "              8 STORE_NAME               2 (__qualname__)\n",
      "\n",
      " 12          10 LOAD_CONST               1 (<code object yelp at 0x7ff12e9510d0, file \"<string>\", line 12>)\n",
      "             12 MAKE_FUNCTION            0\n",
      "             14 STORE_NAME               3 (yelp)\n",
      "\n",
      " 14          16 LOAD_CONST               2 (<code object hunt at 0x7ff12e950e30, file \"<string>\", line 14>)\n",
      "             18 MAKE_FUNCTION            0\n",
      "             20 STORE_NAME               4 (hunt)\n",
      "             22 LOAD_CONST               3 (None)\n",
      "             24 RETURN_VALUE\n",
      "\n",
      "Disassembly of <code object yelp at 0x7ff12e9510d0, file \"<string>\", line 12>:\n",
      " 12           0 RESUME                   0\n",
      "\n",
      " 13           2 LOAD_GLOBAL              1 (NULL + print)\n",
      "             14 LOAD_CONST               1 ('WOOF!')\n",
      "             16 PRECALL                  1\n",
      "             20 CALL                     1\n",
      "             30 POP_TOP\n",
      "             32 LOAD_CONST               0 (None)\n",
      "             34 RETURN_VALUE\n",
      "\n",
      "Disassembly of <code object hunt at 0x7ff12e950e30, file \"<string>\", line 14>:\n",
      " 14           0 RESUME                   0\n",
      "\n",
      " 15           2 LOAD_GLOBAL              1 (NULL + print)\n",
      "             14 LOAD_CONST               1 ('hunting')\n",
      "             16 PRECALL                  1\n",
      "             20 CALL                     1\n",
      "             30 POP_TOP\n",
      "             32 LOAD_CONST               0 (None)\n",
      "             34 RETURN_VALUE\n",
      "\n",
      "Disassembly of <code object SnifferDog at 0x7ff12e94c6b0, file \"<string>\", line 17>:\n",
      " 17           0 RESUME                   0\n",
      "              2 LOAD_NAME                0 (__name__)\n",
      "              4 STORE_NAME               1 (__module__)\n",
      "              6 LOAD_CONST               0 ('SnifferDog')\n",
      "              8 STORE_NAME               2 (__qualname__)\n",
      "\n",
      " 18          10 LOAD_CONST               1 (<code object search at 0x7ff12e9517d0, file \"<string>\", line 18>)\n",
      "             12 MAKE_FUNCTION            0\n",
      "             14 STORE_NAME               3 (search)\n",
      "             16 LOAD_CONST               2 (None)\n",
      "             18 RETURN_VALUE\n",
      "\n",
      "Disassembly of <code object search at 0x7ff12e9517d0, file \"<string>\", line 18>:\n",
      " 18           0 RESUME                   0\n",
      "\n",
      " 19           2 LOAD_GLOBAL              1 (NULL + print)\n",
      "             14 LOAD_CONST               1 ('searching')\n",
      "             16 PRECALL                  1\n",
      "             20 CALL                     1\n",
      "             30 POP_TOP\n",
      "             32 LOAD_CONST               0 (None)\n",
      "             34 RETURN_VALUE\n",
      "\n",
      "Disassembly of <code object PoliceDog at 0x7ff12e94e800, file \"<string>\", line 21>:\n",
      " 21           0 RESUME                   0\n",
      "              2 LOAD_NAME                0 (__name__)\n",
      "              4 STORE_NAME               1 (__module__)\n",
      "              6 LOAD_CONST               0 ('PoliceDog')\n",
      "              8 STORE_NAME               2 (__qualname__)\n",
      "\n",
      " 22          10 LOAD_CONST               1 (<code object patrol at 0x7ff12e952170, file \"<string>\", line 22>)\n",
      "             12 MAKE_FUNCTION            0\n",
      "             14 STORE_NAME               3 (patrol)\n",
      "             16 LOAD_CONST               2 (None)\n",
      "             18 RETURN_VALUE\n",
      "\n",
      "Disassembly of <code object patrol at 0x7ff12e952170, file \"<string>\", line 22>:\n",
      " 22           0 RESUME                   0\n",
      "\n",
      " 23           2 LOAD_GLOBAL              1 (NULL + print)\n",
      "             14 LOAD_CONST               1 ('patroling')\n",
      "             16 PRECALL                  1\n",
      "             20 CALL                     1\n",
      "             30 POP_TOP\n",
      "             32 LOAD_CONST               0 (None)\n",
      "             34 RETURN_VALUE\n",
      "None\n"
     ]
    }
   ],
   "execution_count": 39
  },
  {
   "metadata": {
    "ExecuteTime": {
     "end_time": "2025-05-04T12:00:36.719265Z",
     "start_time": "2025-05-04T12:00:36.712989Z"
    }
   },
   "cell_type": "code",
   "source": [
    "class A:\n",
    "    pass\n",
    "\n",
    "class B(A):\n",
    "    pass\n",
    "\n",
    "class C(B):\n",
    "    pass\n",
    "\n",
    "class D(A):\n",
    "    pass\n",
    "\n",
    "class E(D):\n",
    "    pass\n",
    "\n",
    "class F(A):\n",
    "    pass\n",
    "\n",
    "class G(C, E, F):\n",
    "    pass\n",
    "\n",
    "# 深度优先\n",
    "print(G.__mro__)"
   ],
   "id": "103910d1e2c98769",
   "outputs": [
    {
     "name": "stdout",
     "output_type": "stream",
     "text": [
      "(<class '__main__.G'>, <class '__main__.C'>, <class '__main__.B'>, <class '__main__.E'>, <class '__main__.D'>, <class '__main__.F'>, <class '__main__.A'>, <class 'object'>)\n"
     ]
    }
   ],
   "execution_count": 36
  },
  {
   "metadata": {},
   "cell_type": "code",
   "outputs": [],
   "execution_count": null,
   "source": "",
   "id": "84ca6ce04fa765a3"
  }
 ],
 "metadata": {
  "kernelspec": {
   "display_name": "Python 3",
   "language": "python",
   "name": "python3"
  },
  "language_info": {
   "codemirror_mode": {
    "name": "ipython",
    "version": 2
   },
   "file_extension": ".py",
   "mimetype": "text/x-python",
   "name": "python",
   "nbconvert_exporter": "python",
   "pygments_lexer": "ipython2",
   "version": "2.7.6"
  }
 },
 "nbformat": 4,
 "nbformat_minor": 5
}
